setup.py
lxy_tools/__init__.py
lxy_tools/json.py
lxy_tools/md5.py
lxy_tools/os.py
lxy_tools.egg-info/PKG-INFO
lxy_tools.egg-info/SOURCES.txt
lxy_tools.egg-info/dependency_links.txt
lxy_tools.egg-info/top_level.txt