Metadata-Version: 2.1
Name: lxy-tools
Version: 0.0.1
Summary: Everyday handy tools
Home-page: 
Author: Xinyu Li
Author-email: neworld001@pku.edu.cn
Classifier: Programming Language :: Python :: 3
Classifier: License :: OSI Approved :: MIT License
Classifier: Operating System :: OS Independent
Requires-Python: >=3.6
